rpi_deep_pantilt/__init__.py
rpi_deep_pantilt/cli.py
rpi_deep_pantilt/control/__init__.py
rpi_deep_pantilt/control/hardware_test.py
rpi_deep_pantilt/control/manager.py
rpi_deep_pantilt/control/pid.py
rpi_deep_pantilt/data/__init__.py
rpi_deep_pantilt/data/facessd_label_map.pbtxt
rpi_deep_pantilt/data/mscoco_label_map.pbtxt
rpi_deep_pantilt/detect/__init__.py
rpi_deep_pantilt/detect/camera.py
rpi_deep_pantilt/detect/facessd_mobilenet_v2.py
rpi_deep_pantilt/detect/ssd_mobilenet_v3_coco.py
rpi_deep_pantilt/detect/util/__init__.py
rpi_deep_pantilt/detect/util/label.py
rpi_deep_pantilt/detect/util/string_int_label_map_pb2.py
rpi_deep_pantilt/detect/util/visualization.py
rpi_deep_pantilt-1.2.1.dist-info/AUTHORS.md
rpi_deep_pantilt-1.2.1.dist-info/LICENSE
rpi_deep_pantilt-1.2.1.dist-info/METADATA
rpi_deep_pantilt-1.2.1.dist-info/WHEEL
rpi_deep_pantilt-1.2.1.dist-info/entry_points.txt
rpi_deep_pantilt-1.2.1.dist-info/top_level.txt
rpi_deep_pantilt-1.2.1.dist-info/RECORD
