Metadata-Version: 2.1
Name: rpi-deep-pantilt
Version: 1.2.1
Summary: An example of deep object detection and tracking with a Raspberry Pi, PiCamera, and Pimoroni Pantilt Hat
Home-page: https://github.com/leigh-johnson/rpi-deep-pantilt
Author: Leigh Johnson
Author-email: hi@leighjohnson.me
License: MIT license
Keywords: computer vision cv tensorflow raspberrypi detection tracking
Platform: UNKNOWN
Classifier: Development Status :: 2 - Pre-Alpha
Classifier: Intended Audience :: Developers
Classifier: License :: OSI Approved :: MIT License
Classifier: Natural Language :: English
Classifier: Programming Language :: Python :: 3.7
Classifier: Programming Language :: Python :: 3.8
Requires-Python: >=3.7
Requires-Dist: Click (>=7.0)
Requires-Dist: pillow
Requires-Dist: h5py
Requires-Dist: tensorflow (>=2.2.0)
Requires-Dist: smbus ; platform_machine == "armv7l"
Requires-Dist: picamera ; platform_machine == "armv7l"
Requires-Dist: pantilthat (>=0.0.7) ; platform_machine == "armv7l"
Requires-Dist: numpy ; platform_machine == "x86_64"
